LICENSE.txt
pyproject.toml
setup.cfg
setup.py
funbeav_package.egg-info/PKG-INFO
funbeav_package.egg-info/SOURCES.txt
funbeav_package.egg-info/dependency_links.txt
funbeav_package.egg-info/requires.txt
funbeav_package.egg-info/top_level.txt
logic/__init__.py
logic/main.py