Metadata-Version: 2.1
Name: funbeav-package
Version: 0.2
Summary: TYPE YOUR DESCRIPTION HERE
Home-page: https://github.com/sidorov97/funbeav
Download-URL: https://github.com/sidorov97/funbeav/archive/refs/tags/v02.tar.gz
Author: Sidorov
Author-email: sidorov_i@rocketdata.iocom
License: MIT
Keywords: SOME,SHIT,KEYWORDS
Platform: UNKNOWN
Classifier: Development Status :: 3 - Alpha
Classifier: Intended Audience :: Developers
Classifier: Topic :: Software Development :: Build Tools
Classifier: License :: OSI Approved :: MIT License
Classifier: Programming Language :: Python :: 3
Classifier: Programming Language :: Python :: 3.4
Classifier: Programming Language :: Python :: 3.5
Classifier: Programming Language :: Python :: 3.6
License-File: LICENSE.txt
